ut_gen/__init__.py
ut_gen/__version__.py
ut_gen/cmd.py
ut_gen/cmdline.py
ut_gen/col.py
ut_gen/evt.py
ut_gen/exc.py
ut_gen/msg.py
ut_gen/py.typed
ut_gen/range.py
ut_gen/utg.py
ut_gen/ver.py
ut_gen/data/__init__.py
ut_gen/data/log.main.tenant.yml
ut_gen/data/log.yml
ut_gen-1.1.0.20250821.dist-info/licenses/LICENSE.txt
ut_gen-1.1.0.20250821.dist-info/METADATA
ut_gen-1.1.0.20250821.dist-info/WHEEL
ut_gen-1.1.0.20250821.dist-info/top_level.txt
ut_gen-1.1.0.20250821.dist-info/RECORD
